movsviewer/__init__.py
movsviewer/automation.py
movsviewer/chartview.py
movsviewer/constants.py
movsviewer/mainui.py
movsviewer/plotutils.py
movsviewer/resources/geckodriver.exe
movsviewer/resources/mainui.ui
movsviewer/resources/settingsui.ui
movsviewer/settings.py
movsviewer/validator.py
movsviewer/viewmodel.py
zeed_movs_viewer-0.0.2.dist-info/METADATA
zeed_movs_viewer-0.0.2.dist-info/WHEEL
zeed_movs_viewer-0.0.2.dist-info/entry_points.txt
zeed_movs_viewer-0.0.2.dist-info/licenses/LICENSE
zeed_movs_viewer-0.0.2.dist-info/RECORD
