Metadata-Version: 2.1
Name: zeed-movs-viewer
Version: 0.0.2
License:                     GNU AFFERO GENERAL PUBLIC LICENSE
Classifier: Programming Language :: Python :: 3 :: Only
Classifier: Programming Language :: Python :: 3.12
Classifier: Programming Language :: Python :: 3.13
Project-URL: Homepage, https://github.com/ZeeD/movs-viewer
Project-URL: Repository, https://github.com/ZeeD/movs-viewer.git
Requires-Python: <3.14,>=3.12
Requires-Dist: pyside6>=6.8.2
Requires-Dist: pythonqwt>=0.12.5
Requires-Dist: selenium>=4.22
Requires-Dist: zeed-guilib>=0.0.4
Requires-Dist: zeed-movs-merger>=0.0.1
Requires-Dist: zeed-movs-validator>=0.0.1
Requires-Dist: zeed-movslib>=0.0.3
